arcus_azureml-1.1.2.2.2022030301-py3.8-nspkg.pth
arcus/azureml/__init__.py
arcus/azureml/projectutils.py
arcus/azureml/version.py
arcus/azureml/datacollection/__init__.py
arcus/azureml/datacollection/kagglecollection.py
arcus/azureml/environment/__init__.py
arcus/azureml/environment/aml_environment.py
arcus/azureml/environment/environment.py
arcus/azureml/environment/environment_factory.py
arcus/azureml/environment/errors.py
arcus/azureml/experimenting/__init__.py
arcus/azureml/experimenting/aml_trainer.py
arcus/azureml/experimenting/errors.py
arcus/azureml/experimenting/train_environment.py
arcus/azureml/experimenting/trainer.py
arcus/azureml/experimenting/tuning.py
arcus/azureml/experimenting/resources/train.py
arcus_azureml-1.1.2.2.2022030301.dist-info/LICENSE
arcus_azureml-1.1.2.2.2022030301.dist-info/METADATA
arcus_azureml-1.1.2.2.2022030301.dist-info/WHEEL
arcus_azureml-1.1.2.2.2022030301.dist-info/namespace_packages.txt
arcus_azureml-1.1.2.2.2022030301.dist-info/top_level.txt
arcus_azureml-1.1.2.2.2022030301.dist-info/RECORD
