Metadata-Version: 2.1
Name: arcus-azureml
Version: 1.1.2.2.2022030301
Summary: A Python library to improve MLOps methodology on Azure Machine Learning
Home-page: https://github.com/arcus-azure/arcus.azureml
Author: Arcus
Author-email: arcus-automation@codit.eu
License: UNKNOWN
Platform: UNKNOWN
Classifier: Programming Language :: Python :: 3
Classifier: License :: OSI Approved :: MIT License
Classifier: Operating System :: OS Independent
Requires-Python: >=3.6
License-File: LICENSE
Requires-Dist: pandas
Requires-Dist: numpy
Requires-Dist: arcus-ml (>=1.0.11)
Requires-Dist: azureml-core
Requires-Dist: joblib
Provides-Extra: testing
Requires-Dist: pytest ; extra == 'testing'
